openimis_be_product-1.9.0.dist-info/licenses/LICENSE.md
product/__init__.py
product/admin.py
product/apps.py
product/dataloaders.py
product/enums.py
product/gql_mutations.py
product/models.py
product/report.py
product/schema.py
product/services.py
product/test_helpers.py
product/urls.py
product/views.py
product/migrations/0001_initial.py
product/migrations/0002_productmutation.py
product/migrations/0003_add_enrollment_officer_gql_query_products_perms.py
product/migrations/0004_alter_product_options.py
product/migrations/0005_add_ceiling_type_column.py
product/migrations/0006_insert_ceiling_type.py
product/migrations/0007_auto_20230510_1347.py
product/migrations/0008_auto_20230510_1347.py
product/migrations/0009_auto_20240129_1008.py
product/migrations/__init__.py
product/reports/__init__.py
product/reports/product_derived_operational_indicators.py
product/reports/product_sales.py
product/tests/__init__.py
product/tests/tests_gql.py
product/tests/tests_services.py
openimis_be_product-1.9.0.dist-info/METADATA
openimis_be_product-1.9.0.dist-info/WHEEL
openimis_be_product-1.9.0.dist-info/top_level.txt
openimis_be_product-1.9.0.dist-info/RECORD
