Metadata-Version: 2.4
Name: openimis-be-product
Version: 1.9.0
Summary: The openIMIS Backend Product reference module.
Home-page: https://openimis.org/
Author: Xavier Gillmann
Author-email: xgillmann@bluesquarehub.com
License: GNU AGPL v3
Classifier: Environment :: Web Environment
Classifier: Framework :: Django
Classifier: Framework :: Django :: 2.1
Classifier: Intended Audience :: Developers
Classifier: License :: OSI Approved :: GNU Affero General Public License v3
Classifier: Operating System :: OS Independent
Classifier: Programming Language :: Python
Classifier: Programming Language :: Python :: 3.6
Classifier: Programming Language :: Python :: 3.7
License-File: LICENSE.md
Requires-Dist: django
Requires-Dist: django-db-signals
Requires-Dist: django-clone
Requires-Dist: djangorestframework
Requires-Dist: openimis-be-location
Dynamic: author
Dynamic: author-email
Dynamic: classifier
Dynamic: home-page
Dynamic: license
Dynamic: license-file
Dynamic: requires-dist
Dynamic: summary
